flyteplugins/__init__.py
flyteplugins/sglang/__init__.py
flyteplugins/sglang/_app_environment.py
flyteplugins/sglang/_constants.py
flyteplugins/sglang/_model_loader/__init__.py
flyteplugins/sglang/_model_loader/shim.py
flyteplugins_sglang-2.0.0b53.dist-info/METADATA
flyteplugins_sglang-2.0.0b53.dist-info/WHEEL
flyteplugins_sglang-2.0.0b53.dist-info/entry_points.txt
flyteplugins_sglang-2.0.0b53.dist-info/top_level.txt
flyteplugins_sglang-2.0.0b53.dist-info/RECORD
